voxelcity/__init__.py
voxelcity/voxelcity.py
voxelcity/download/__init__.py
voxelcity/download/eubucco.py
voxelcity/download/gee.py
voxelcity/download/mbfp.py
voxelcity/download/oemj.py
voxelcity/download/omt.py
voxelcity/download/osm.py
voxelcity/download/overture.py
voxelcity/download/utils.py
voxelcity/file/__init_.py
voxelcity/file/envimet.py
voxelcity/file/geojson.py
voxelcity/file/magicavoxel.py
voxelcity/file/obj.py
voxelcity/geo/__init_.py
voxelcity/geo/draw.py
voxelcity/geo/grid.py
voxelcity/geo/utils.py
voxelcity/sim/__init_.py
voxelcity/sim/view.py
voxelcity/utils/__init_.py
voxelcity/utils/lc.py
voxelcity/utils/visualization.py
voxelcity-0.1.81.dist-info/AUTHORS.rst
voxelcity-0.1.81.dist-info/LICENSE
voxelcity-0.1.81.dist-info/METADATA
voxelcity-0.1.81.dist-info/WHEEL
voxelcity-0.1.81.dist-info/top_level.txt
voxelcity-0.1.81.dist-info/RECORD
