Metadata-Version: 2.1
Name: voxelcity
Version: 0.1.81
Summary: voxelcity is an easy and one-stop tool to output 3d city models for microclimate simulation by integrating multiple geospatial open-data
Author-email: Kunihiko Fujiwara <kunihiko@nus.edu.sg>
Maintainer-email: Kunihiko Fujiwara <kunihiko@nus.edu.sg>
License: MIT
Project-URL: bugs, https://github.com/kunifujiwara/voxelcity/issues
Project-URL: changelog, https://github.com/kunifujiwara/voxelcity/blob/master/changelog.md
Project-URL: homepage, https://github.com/kunifujiwara/voxelcity
Classifier: Programming Language :: Python :: 3.10
Classifier: Programming Language :: Python :: 3.11
Classifier: Programming Language :: Python :: 3.12
Requires-Python: <3.13,>=3.10
License-File: LICENSE
License-File: AUTHORS.rst
Requires-Dist: typer
Requires-Dist: pandas
Requires-Dist: requests
Requires-Dist: pyproj
Requires-Dist: ipyleaflet
Requires-Dist: geopandas
Requires-Dist: rasterio==1.3.11
Requires-Dist: shapely
Requires-Dist: gdown
Requires-Dist: numpy
Requires-Dist: matplotlib
Requires-Dist: contextily
Requires-Dist: fiona
Requires-Dist: rtree
Requires-Dist: plotly
Requires-Dist: tqdm
Requires-Dist: scipy
Requires-Dist: affine
Requires-Dist: earthengine-api
Requires-Dist: geemap
Requires-Dist: rio-cogeo
Requires-Dist: geopy
Requires-Dist: py-vox-io
Requires-Dist: mapbox_vector_tile
Requires-Dist: numba
Requires-Dist: reverse_geocoder
Requires-Dist: pycountry
Requires-Dist: osm2geojson
Requires-Dist: seaborn
Requires-Dist: overturemaps
Requires-Dist: protobuf==3.20.3
Requires-Dist: timezonefinder
Provides-Extra: dev
Requires-Dist: coverage; extra == "dev"
Requires-Dist: mypy; extra == "dev"
Requires-Dist: pytest; extra == "dev"
Requires-Dist: ruff; extra == "dev"
